peft/__init__.py
peft/auto.py
peft/config.py
peft/helpers.py
peft/import_utils.py
peft/mapping.py
peft/mixed_model.py
peft/peft_model.py
peft/py.typed
peft/tuners/__init__.py
peft/tuners/lycoris_utils.py
peft/tuners/tuners_utils.py
peft/tuners/adalora/__init__.py
peft/tuners/adalora/bnb.py
peft/tuners/adalora/config.py
peft/tuners/adalora/gptq.py
peft/tuners/adalora/layer.py
peft/tuners/adalora/model.py
peft/tuners/adaption_prompt/__init__.py
peft/tuners/adaption_prompt/config.py
peft/tuners/adaption_prompt/layer.py
peft/tuners/adaption_prompt/model.py
peft/tuners/adaption_prompt/utils.py
peft/tuners/ia3/__init__.py
peft/tuners/ia3/bnb.py
peft/tuners/ia3/config.py
peft/tuners/ia3/layer.py
peft/tuners/ia3/model.py
peft/tuners/loha/__init__.py
peft/tuners/loha/config.py
peft/tuners/loha/layer.py
peft/tuners/loha/model.py
peft/tuners/lokr/__init__.py
peft/tuners/lokr/config.py
peft/tuners/lokr/layer.py
peft/tuners/lokr/model.py
peft/tuners/lora/__init__.py
peft/tuners/lora/aqlm.py
peft/tuners/lora/awq.py
peft/tuners/lora/bnb.py
peft/tuners/lora/config.py
peft/tuners/lora/gptq.py
peft/tuners/lora/layer.py
peft/tuners/lora/model.py
peft/tuners/lora/tp_layer.py
peft/tuners/mixed/__init__.py
peft/tuners/mixed/model.py
peft/tuners/multitask_prompt_tuning/__init__.py
peft/tuners/multitask_prompt_tuning/config.py
peft/tuners/multitask_prompt_tuning/model.py
peft/tuners/oft/__init__.py
peft/tuners/oft/config.py
peft/tuners/oft/layer.py
peft/tuners/oft/model.py
peft/tuners/p_tuning/__init__.py
peft/tuners/p_tuning/config.py
peft/tuners/p_tuning/model.py
peft/tuners/poly/__init__.py
peft/tuners/poly/config.py
peft/tuners/poly/layer.py
peft/tuners/poly/model.py
peft/tuners/poly/router.py
peft/tuners/prefix_tuning/__init__.py
peft/tuners/prefix_tuning/config.py
peft/tuners/prefix_tuning/model.py
peft/tuners/prompt_tuning/__init__.py
peft/tuners/prompt_tuning/config.py
peft/tuners/prompt_tuning/model.py
peft/utils/__init__.py
peft/utils/constants.py
peft/utils/integrations.py
peft_patched-0.9.3.dist-info/LICENSE
peft_patched-0.9.3.dist-info/METADATA
peft_patched-0.9.3.dist-info/WHEEL
peft_patched-0.9.3.dist-info/top_level.txt
peft_patched-0.9.3.dist-info/RECORD
